README.rst
setup.py
Flask_Negotiation.egg-info/PKG-INFO
Flask_Negotiation.egg-info/SOURCES.txt
Flask_Negotiation.egg-info/dependency_links.txt
Flask_Negotiation.egg-info/not-zip-safe
Flask_Negotiation.egg-info/requires.txt
Flask_Negotiation.egg-info/top_level.txt
flask_negotiation/__init__.py
flask_negotiation/decorators.py
flask_negotiation/media_type.py
flask_negotiation/renderers.py