Metadata-Version: 1.1
Name: Flask-Negotiation
Version: 0.1.5
Summary: Better content negotiation for flask
Home-page: http://blog.hardtack.me/
Author: GunWoo Choi
Author-email: 6566gun@gmail.com
License: UNKNOWN
Platform: any
Classifier: Development Status :: 4 - Beta
Classifier: Environment :: Web Environment
Classifier: Intended Audience :: Developers
